serveliza/__init__.py
serveliza/cli.py
serveliza/serveliza.py
serveliza/mixins/__init__.py
serveliza/mixins/pdf.py
serveliza/mixins/pdf_processors.py
serveliza/roll/__init__.py
serveliza/roll/adapters.py
serveliza/roll/exporter.py
serveliza/roll/memorizer.py
serveliza/roll/parsers.py
serveliza/roll/printer.py
serveliza/roll/roll.py
serveliza/utils/DPA-commune-circuns.json
serveliza/utils/DPA.py
serveliza/utils/__init__.py
serveliza/utils/humanize.py
serveliza/utils/pdf.py
serveliza-0.1.7.dist-info/AUTHORS.rst
serveliza-0.1.7.dist-info/LICENSE
serveliza-0.1.7.dist-info/METADATA
serveliza-0.1.7.dist-info/WHEEL
serveliza-0.1.7.dist-info/entry_points.txt
serveliza-0.1.7.dist-info/top_level.txt
serveliza-0.1.7.dist-info/RECORD
