Metadata-Version: 2.1
Name: serveliza
Version: 0.1.7
Summary: Serveliza description
Home-page: https://github.com/chivke/serveliza
Author: chivke
Author-email: chivke@pm.me
License: GNU General Public License v3
Keywords: serveliza
Platform: UNKNOWN
Classifier: Development Status :: 3 - Alpha
Classifier: Intended Audience :: Developers
Classifier: License :: OSI Approved :: GNU General Public License v3 (GPLv3)
Classifier: Natural Language :: English
Classifier: Programming Language :: Python :: 3
Classifier: Programming Language :: Python :: 3.6
Classifier: Programming Language :: Python :: 3.7
Classifier: Programming Language :: Python :: 3.8
Requires-Python: >=3.6
Requires-Dist: pdftotext (==2.1.5)
Requires-Dist: pandas (==1.1.3)
Requires-Dist: python-slugify (==4.0.1)
Requires-Dist: pdfminer.six (==20200726)
Requires-Dist: pyyaml (==5.3.1)
